<?xml version="1.0" encoding="UTF-8"?>
<odoo>
    <template id="products_request_cost" inherit_id="website_sale.product">
        <xpath expr="//t[@t-call='website_sale.product_price']" position="attributes">
            <attribute name="t-if">not product.request_quote</attribute>
        </xpath>
        <xpath expr="//p[@t-if='True']" position="attributes">
            <attribute name="t-if">True and not product.request_quote</attribute>
        </xpath>
        <xpath expr="//a[@id='add_to_cart']" position="attributes">
            <attribute name="t-if">not product.request_quote</attribute>
        </xpath>
        <xpath expr="//a[@id='add_to_cart']" position="before">
            <a t-if="product.request_quote" role="button" id="ace_request_form" class="btn btn-primary btn-lg mt8 js_check_product" t-att-href="'%s' % (product.request_url or '/get-quote')">Request for quote</a>
        </xpath>
        <xpath expr="//p[@t-else='']" position="replace">
            <p t-elif="not product.request_quote" class="alert alert-warning">This product has no valid combination.</p>
        </xpath>
    </template>

    <template id="product_quantity_request_quote" inherit_id="website_sale.product_quantity">
        <xpath expr="//div[hasclass('ks_quantity_panel')]" position="attributes">
            <attribute name="t-if">not product.request_quote</attribute>
        </xpath>
    </template>

    <template id="products_item_request_quote" inherit_id="ks_theme_kinetik.ks_change_b_tag">
        <xpath expr="//div[hasclass('ks-price')]" position="attributes">
            <attribute name="t-if">not product.request_quote</attribute>
        </xpath>
    </template>
</odoo>